README
setup.cfg
setup.py
pyflu/__init__.py
pyflu/abc.py
pyflu/command.py
pyflu/containerutils.py
pyflu/daemon.py
pyflu/date_navigator.py
pyflu/encoding.py
pyflu/fifo.py
pyflu/formating.py
pyflu/getopt_app.py
pyflu/jsonalize.py
pyflu/modules.py
pyflu/odict.py
pyflu/path.py
pyflu/phony.py
pyflu/profile.py
pyflu/shell_color.py
pyflu/translation.py
pyflu.egg-info/PKG-INFO
pyflu.egg-info/SOURCES.txt
pyflu.egg-info/dependency_links.txt
pyflu.egg-info/entry_points.txt
pyflu.egg-info/top_level.txt
pyflu/meta/__init__.py
pyflu/meta/conflict.py
pyflu/meta/inherit.py
pyflu/qt/__init__.py
pyflu/qt/duck_widgets.py
pyflu/qt/graphics.py
pyflu/qt/util.py
pyflu/qt/base/__init__.py
pyflu/qt/base/main_window.py
pyflu/qt/bug_report/__init__.py
pyflu/qt/bug_report/dialog.py
pyflu/qt/bug_report/settings.py
pyflu/qt/bug_report/tb.py
pyflu/qt/bug_report/ui_dialog.py
pyflu/qt/models/__init__.py
pyflu/qt/models/tablemodel.py
pyflu/qt/models/tablenode.py
pyflu/qt/models/treemodel.py
pyflu/qt/models/treenode.py
pyflu/qt/views/__init__.py
pyflu/qt/views/treenode_view.py
pyflu/qt/widgets/__init__.py
pyflu/qt/widgets/base_type_widgets.py
pyflu/setuptools/__init__.py
pyflu/setuptools/base.py
pyflu/setuptools/cython.py
pyflu/setuptools/nsis.py
pyflu/setuptools/qt.py
pyflu/setuptools/update.py
pyflu/setuptools/versioning.py
pyflu/tests/__init__.py
pyflu/tests/test_jsonalize.py
pyflu/tests/test_update/__init__.py
pyflu/tests/test_update/test_qt.py
pyflu/update/__init__.py
pyflu/update/qt.py
pyflu/update/remote.py
pyflu/update/signals.py
pyflu/update/version.py