Metadata-Version: 1.1
Name: pyflu
Version: 0.9.7
Summary: A collection of Python utilities.
Home-page: http://projects.luper.fr/misc/wiki/pyflu
Author: Luper Rouch
Author-email: luper.rouch@gmail.com
License: UNKNOWN
Platform: UNKNOWN
Classifier: Development Status :: 3 - Alpha
Classifier: Intended Audience :: Developers
Classifier: License :: OSI Approved :: BSD License
Classifier: Topic :: Software Development :: Libraries :: Python Modules
